teedoc_plugin_search/__init__.py
teedoc_plugin_search/trans_finish.py
teedoc_plugin_search/trans_prepare.py
teedoc_plugin_search/assets/cancel.svg
teedoc_plugin_search/assets/close.svg
teedoc_plugin_search/assets/search.svg
teedoc_plugin_search/assets/search_main.js
teedoc_plugin_search/assets/style.css
teedoc_plugin_search/assets/up.svg
teedoc_plugin_search/locales/ja/LC_MESSAGES/messages.mo
teedoc_plugin_search/locales/ja/LC_MESSAGES/messages.po
teedoc_plugin_search/locales/zh_CN/LC_MESSAGES/messages.mo
teedoc_plugin_search/locales/zh_CN/LC_MESSAGES/messages.po
teedoc_plugin_search-1.5.3.dist-info/LICENSE
teedoc_plugin_search-1.5.3.dist-info/METADATA
teedoc_plugin_search-1.5.3.dist-info/WHEEL
teedoc_plugin_search-1.5.3.dist-info/top_level.txt
teedoc_plugin_search-1.5.3.dist-info/RECORD
